mosaik_components/powerplant/Simulator.py
mosaik_components/powerplant/__init__.py
mosaik_powerplant-0.1.0.dist-info/AUTHORS.txt
mosaik_powerplant-0.1.0.dist-info/LICENSE
mosaik_powerplant-0.1.0.dist-info/METADATA
mosaik_powerplant-0.1.0.dist-info/WHEEL
mosaik_powerplant-0.1.0.dist-info/RECORD
