Metadata-Version: 2.1
Name: mosaik-powerplant
Version: 0.1.0
Summary: Simulator for Powerplants in mosaik
License: MIT
Author: Malte Trauernicht
Author-email: mosaik@offis.de
Requires-Python: >=3.9,<4.0
Classifier: License :: OSI Approved :: MIT License
Classifier: Programming Language :: Python :: 3
Classifier: Programming Language :: Python :: 3.9
Classifier: Programming Language :: Python :: 3.10
Classifier: Programming Language :: Python :: 3.11
Classifier: Programming Language :: Python :: 3.12
Requires-Dist: mosaik-api-v3 (>=3.0.7,<4.0.0)
